pfgadgets/__init__.py
pfgadgets/pfgadgets.py
pfgadgets-0.0.2.dist-info/LICENSE.txt
pfgadgets-0.0.2.dist-info/METADATA
pfgadgets-0.0.2.dist-info/WHEEL
pfgadgets-0.0.2.dist-info/top_level.txt
pfgadgets-0.0.2.dist-info/RECORD
