Metadata-Version: 2.1
Name: pfgadgets
Version: 0.0.2
Summary: A Python package to assist in the use of Python within PowerFactory
Home-page: https://github.com/amcd13/pfgadgets
Author: Andrew McDermott
Author-email: andrew.mcdermott13@gmail.com
License: MIT
License-File: LICENSE.txt
